pbl6packageg2/config/__init__.py
pbl6packageg2/config/env_config.py
pbl6packageg2/emailhelper/__init__.py
pbl6packageg2/emailhelper/config_email.py
pbl6packageg2-0.0.1.dist-info/LICENSE
pbl6packageg2-0.0.1.dist-info/METADATA
pbl6packageg2-0.0.1.dist-info/WHEEL
pbl6packageg2-0.0.1.dist-info/top_level.txt
pbl6packageg2-0.0.1.dist-info/RECORD
