Metadata-Version: 2.1
Name: pbl6packageg2
Version: 0.0.1
Summary: PBL6
Home-page: https://github.com/banhmysuawx/PBL6-BE
Author: Group2
License: MIT
Keywords: django,djangorestframework,drf,rest-client
Classifier: Programming Language :: Python :: 3
Classifier: License :: OSI Approved :: MIT License
Classifier: Operating System :: OS Independent
Requires-Python: >=3.8
License-File: LICENSE
